{
	"name": "Sched_Load_IMPR_L0",
	"properties": {
		"annotations": [],
		"runtimeState": "Started",
		"pipelines": [
			{
				"pipelineReference": {
					"referenceName": "LOAD_IMPR_L0",
					"type": "PipelineReference"
				},
				"parameters": {
					"EXEC_ENV": "prod"
				}
			}
		],
		"type": "ScheduleTrigger",
		"typeProperties": {
			"recurrence": {
				"frequency": "Day",
				"interval": 1,
				"startTime": "2019-12-19T13:25:00.000Z",
				"timeZone": "UTC",
				"schedule": {
					"minutes": [
						30
					],
					"hours": [
						13
					]
				}
			}
		}
	}
}